CHANGES.txt
MANIFEST.in
README.md
setup.py
GeobricksSpatialQuery.egg-info/PKG-INFO
GeobricksSpatialQuery.egg-info/SOURCES.txt
GeobricksSpatialQuery.egg-info/dependency_links.txt
GeobricksSpatialQuery.egg-info/requires.txt
GeobricksSpatialQuery.egg-info/top_level.txt
geobricks_spatial_query/__init__.py
geobricks_spatial_query/__init__.pyc
geobricks_spatial_query/config/__init__.py
geobricks_spatial_query/config/__init__.pyc
geobricks_spatial_query/config/config.py
geobricks_spatial_query/config/config.pyc
geobricks_spatial_query/config/config.py~
geobricks_spatial_query/core/__init__.py
geobricks_spatial_query/core/__init__.pyc
geobricks_spatial_query/core/spatial_query_core.py
geobricks_spatial_query/core/spatial_query_core.pyc
geobricks_spatial_query/rest/__init__.py
geobricks_spatial_query/rest/__init__.pyc
geobricks_spatial_query/rest/spatial_query_main.py
geobricks_spatial_query/rest/spatial_query_rest.py
geobricks_spatial_query/rest/spatial_query_rest.pyc
geobricks_spatial_query/utils/__init__.py
geobricks_spatial_query/utils/__init__.pyc
geobricks_spatial_query/utils/encode_postgis.py
geobricks_spatial_query/utils/encode_postgis.pyc
geobricks_spatial_query/utils/geojson.py
geobricks_spatial_query/utils/geojson.pyc
geobricks_spatial_query/utils/geojson_compression.py
geobricks_spatial_query/utils/geojson_encoder.py
geobricks_spatial_query/utils/geojson_encoder.pyc
geobricks_spatial_query/utils/log.pyc