Metadata-Version: 1.0
Name: GeobricksSpatialQuery
Version: 0.0.8
Summary: Geobricks library to handle spatial queries.
Home-page: http://pypi.python.org/pypi/GeobricksSpatialQuery/
Author: Simone Murzilli; Guido Barbaglia
Author-email: geobrickspy@gmail.com
License: LICENSE.txt
Keywords: geobricks,postgis,gis,statistics,geostatistics,spatial,spatial query
Platform: UNKNOWN
